cachecore/__init__.py
cachecore/serializers.py
cachecore/utils.py
cachecore/caches/__init__.py
cachecore/caches/base.py
cachecore/caches/dummy.py
cachecore/caches/file.py
cachecore/caches/local.py
cachecore/caches/memcached.py
cachecore/caches/redis.py
cachecore-0.4.0.dist-info/LICENSE
cachecore-0.4.0.dist-info/METADATA
cachecore-0.4.0.dist-info/WHEEL
cachecore-0.4.0.dist-info/top_level.txt
cachecore-0.4.0.dist-info/RECORD
