Metadata-Version: 2.1
Name: cachecore
Version: 0.4.0
Summary: A low level cache library.
Home-page: https://github.com/rykroon/cachecore
Author: Ryan Kroon
Author-email: rykroon.tech@gmail.com
License: UNKNOWN
Project-URL: Source Code, https://github.com/rykroon/cachecore/
Project-URL: Bug Tracker, https://github.com/rykroon/cachecore/issues
Platform: UNKNOWN
Classifier: Programming Language :: Python :: 3
Classifier: License :: OSI Approved :: MIT License
Classifier: Operating System :: OS Independent
Requires-Python: >=3.9
License-File: LICENSE
